README.md
setup.cfg
setup.py
pyvisionproductsearch/ProductSearch.py
pyvisionproductsearch/__init__.py
pyvisionproductsearch.egg-info/PKG-INFO
pyvisionproductsearch.egg-info/SOURCES.txt
pyvisionproductsearch.egg-info/dependency_links.txt
pyvisionproductsearch.egg-info/requires.txt
pyvisionproductsearch.egg-info/top_level.txt
test/test_ProductSearch.py