Metadata-Version: 2.1
Name: pyvisionproductsearch
Version: 0.4
Summary: Python Wrapper around the Google Vision Product Search API
Home-page: https://github.com/google/pyvisionproductsearch
Author: Dale Markowitz
Author-email: dale@dalemarkowitz.com
License: apache-2.0
Download-URL: https://github.com/google/pyvisionproductsearch/archive/v0.4.tar.gz
Keywords: google cloud,product search,vision,machine learning
Platform: UNKNOWN
Classifier: Development Status :: 3 - Alpha
Classifier: Intended Audience :: Developers
Classifier: Topic :: Internet
Classifier: License :: OSI Approved :: Apache Software License
Classifier: Programming Language :: Python :: 3.5
Classifier: Programming Language :: Python :: 3.6
